pypom_navigation/__init__.py
pypom_navigation/navigation.py
pypom_navigation/plugin.py
pypom_navigation/util.py
pypom_navigation/pages/__init__.py
pypom_navigation/pages/base.py
pytest_pypom_navigation-2.0.3.dist-info/DESCRIPTION.rst
pytest_pypom_navigation-2.0.3.dist-info/METADATA
pytest_pypom_navigation-2.0.3.dist-info/RECORD
pytest_pypom_navigation-2.0.3.dist-info/WHEEL
pytest_pypom_navigation-2.0.3.dist-info/entry_points.txt
pytest_pypom_navigation-2.0.3.dist-info/metadata.json
pytest_pypom_navigation-2.0.3.dist-info/top_level.txt
