Metadata-Version: 2.0
Name: pytest-pypom-navigation
Version: 2.0.3
Summary: Core engine for cookiecutter-qa and pytest-play packages
Home-page: https://github.com/davidemoro/pytest-pypom-navigation
Author: Davide Moro
Author-email: davide.moro@gmail.com
Maintainer: Davide Moro
Maintainer-email: davide.moro@gmail.com
License: Apache Software License 2.0
Platform: UNKNOWN
Classifier: Development Status :: 4 - Beta
Classifier: Framework :: Pytest
Classifier: Intended Audience :: Developers
Classifier: Topic :: Software Development :: Testing
Classifier: Programming Language :: Python
Classifier: Programming Language :: Python :: 2
Classifier: Programming Language :: Python :: 2.7
Classifier: Programming Language :: Python :: 3
Classifier: Programming Language :: Python :: 3.3
Classifier: Programming Language :: Python :: 3.4
Classifier: Programming Language :: Python :: 3.5
Classifier: Programming Language :: Python :: Implementation :: CPython
Classifier: Programming Language :: Python :: Implementation :: PyPy
Classifier: Operating System :: OS Independent
Classifier: License :: OSI Approved :: Apache Software License
Provides-Extra: docs
Provides-Extra: tests
Requires-Dist: pytest (>=3.0.7)
Requires-Dist: parametrizer
Requires-Dist: pypom-form
Requires-Dist: pytest-variables[yaml]
Requires-Dist: zope.dottedname
Provides-Extra: docs
Requires-Dist: Sphinx; extra == 'docs'
Requires-Dist: sphinx-rtd-theme; extra == 'docs'
Provides-Extra: tests
Requires-Dist: tox; extra == 'tests'
Requires-Dist: pytest-cov; extra == 'tests'
Requires-Dist: mock; extra == 'tests'
